ai_news_collector_lib/__init__.py
ai_news_collector_lib/cli.py
ai_news_collector_lib/config/__init__.py
ai_news_collector_lib/config/api_keys.py
ai_news_collector_lib/config/settings.py
ai_news_collector_lib/core/__init__.py
ai_news_collector_lib/core/advanced_collector.py
ai_news_collector_lib/core/collector.py
ai_news_collector_lib/examples/__init__.py
ai_news_collector_lib/examples/advanced_usage.py
ai_news_collector_lib/examples/basic_usage.py
ai_news_collector_lib/models/__init__.py
ai_news_collector_lib/models/article.py
ai_news_collector_lib/models/enhanced_query.py
ai_news_collector_lib/models/result.py
ai_news_collector_lib/tests/__init__.py
ai_news_collector_lib/tests/test_basic.py
ai_news_collector_lib/tools/__init__.py
ai_news_collector_lib/tools/search_tools.py
ai_news_collector_lib/utils/__init__.py
ai_news_collector_lib/utils/cache.py
ai_news_collector_lib/utils/content_extractor.py
ai_news_collector_lib/utils/keyword_extractor.py
ai_news_collector_lib/utils/query_enhancer.py
ai_news_collector_lib/utils/reporter.py
ai_news_collector_lib/utils/scheduler.py
ai_news_collector_lib-0.1.3.dist-info/licenses/LICENSE
ai_news_collector_lib-0.1.3.dist-info/METADATA
ai_news_collector_lib-0.1.3.dist-info/WHEEL
ai_news_collector_lib-0.1.3.dist-info/entry_points.txt
ai_news_collector_lib-0.1.3.dist-info/top_level.txt
ai_news_collector_lib-0.1.3.dist-info/RECORD
