Metadata-Version: 2.4
Name: ai-news-collector-lib
Version: 0.1.3
Summary: A Python library for collecting AI-related news from multiple sources
Home-page: https://github.com/ai-news-collector/ai-news-collector-lib
Author: AI News Collector Team
Author-email: AI News Collector Team <support@ai-news-collector.com>
Maintainer-email: AI News Collector Team <support@ai-news-collector.com>
License: MIT
Project-URL: Homepage, https://github.com/ai-news-collector/ai-news-collector-lib
Project-URL: Documentation, https://ai-news-collector-lib.readthedocs.io/
Project-URL: Repository, https://github.com/ai-news-collector/ai-news-collector-lib.git
Project-URL: Bug Tracker, https://github.com/ai-news-collector/ai-news-collector-lib/issues
Keywords: ai,news,collector,search,web scraping,machine learning,artificial intelligence
Classifier: Development Status :: 4 - Beta
Classifier: Intended Audience :: Developers
Classifier: License :: OSI Approved :: MIT License
Classifier: Operating System :: OS Independent
Classifier: Programming Language :: Python :: 3
Classifier: Programming Language :: Python :: 3.8
Classifier: Programming Language :: Python :: 3.9
Classifier: Programming Language :: Python :: 3.10
Classifier: Programming Language :: Python :: 3.11
Classifier: Topic :: Software Development :: Libraries :: Python Modules
Classifier: Topic :: Internet :: WWW/HTTP :: Indexing/Search
Classifier: Topic :: Scientific/Engineering :: Artificial Intelligence
Requires-Python: >=3.8
License-File: LICENSE
Requires-Dist: requests>=2.28.0
Requires-Dist: beautifulsoup4>=4.11.0
Requires-Dist: feedparser>=6.0.0
Requires-Dist: python-dotenv>=0.19.0
Requires-Dist: google-generativeai>=0.3.0
Provides-Extra: advanced
Requires-Dist: aiohttp>=3.8.0; extra == "advanced"
Requires-Dist: redis>=4.0.0; extra == "advanced"
Requires-Dist: schedule>=1.2.0; extra == "advanced"
Requires-Dist: apscheduler>=3.9.0; extra == "advanced"
Provides-Extra: nlp
Requires-Dist: nltk>=3.8; extra == "nlp"
Requires-Dist: spacy>=3.4.0; extra == "nlp"
Requires-Dist: textblob>=0.17.0; extra == "nlp"
Provides-Extra: web
Requires-Dist: fastapi>=0.80.0; extra == "web"
Requires-Dist: uvicorn>=0.18.0; extra == "web"
Requires-Dist: streamlit>=1.20.0; extra == "web"
Provides-Extra: dev
Requires-Dist: pytest>=7.0.0; extra == "dev"
Requires-Dist: pytest-asyncio>=0.20.0; extra == "dev"
Requires-Dist: black>=22.0.0; extra == "dev"
Requires-Dist: flake8>=5.0.0; extra == "dev"
Requires-Dist: mypy>=0.950; extra == "dev"
Requires-Dist: vcrpy>=4.4.0; extra == "dev"
Dynamic: author
Dynamic: home-page
Dynamic: license-file
Dynamic: requires-python
